rubicon_java-0.2.5-py3.9-nspkg.pth
rubicon/java/__init__.py
rubicon/java/android_events.py
rubicon/java/api.py
rubicon/java/jni.py
rubicon/java/types.py
rubicon_java-0.2.5.dist-info/LICENSE
rubicon_java-0.2.5.dist-info/METADATA
rubicon_java-0.2.5.dist-info/WHEEL
rubicon_java-0.2.5.dist-info/namespace_packages.txt
rubicon_java-0.2.5.dist-info/top_level.txt
rubicon_java-0.2.5.dist-info/RECORD
