Metadata-Version: 2.1
Name: rubicon-java
Version: 0.2.5
Summary: A bridge between the Java Runtime Environment and Python.
Home-page: https://beeware.org/rubicon
Author: Russell Keith-Magee
Author-email: russell@keith-magee.com
License: New BSD
Project-URL: Funding, https://beeware.org/contributing/membership/
Project-URL: Documentation, https://rubicon-java.readthedocs.io/en/latest/
Project-URL: Tracker, https://github.com/beeware/rubicon-java/issues
Project-URL: Source, https://github.com/beeware/rubicon-java
Platform: UNKNOWN
Classifier: Development Status :: 4 - Beta
Classifier: Intended Audience :: Developers
Classifier: License :: OSI Approved :: BSD License
Classifier: Programming Language :: Java
Classifier: Programming Language :: Python :: 3
Classifier: Programming Language :: Python :: 3.5
Classifier: Programming Language :: Python :: 3.6
Classifier: Programming Language :: Python :: 3.7
Classifier: Programming Language :: Python :: 3.8
Classifier: Programming Language :: Python :: 3 :: Only
Classifier: Topic :: Software Development
Requires-Python: >=3.5
